glue/__init__.py
glue/lal.py
glue/pidfile.py
glue/pipeline.py
glue/text_progress_bar.py
glue/utils.py
glue/tests/__init__.py
glue/tests/test_lal.py
glue/tests/test_pidfile.py
glue/tests/test_pipeline.py
lscsoft_glue-4.1.0.dist-info/LICENSE
lscsoft_glue-4.1.0.dist-info/METADATA
lscsoft_glue-4.1.0.dist-info/WHEEL
lscsoft_glue-4.1.0.dist-info/top_level.txt
lscsoft_glue-4.1.0.dist-info/RECORD
